mstk/__init__.py
mstk/errors.py
mstk/analyzer/__init__.py
mstk/analyzer/canny.py
mstk/analyzer/energy_kernels.py
mstk/analyzer/ewald.py
mstk/analyzer/fitting.py
mstk/analyzer/neighborlist.py
mstk/analyzer/series.py
mstk/analyzer/structure.py
mstk/analyzer/vle.py
mstk/chem/__init__.py
mstk/chem/constant.py
mstk/chem/element.py
mstk/chem/formula.py
mstk/cli/__init__.py
mstk/cli/analyze_rdf.py
mstk/cli/build.py
mstk/cli/export.py
mstk/cli/ffconv.py
mstk/cli/logplot.py
mstk/cli/topconv.py
mstk/cli/trjconv.py
mstk/cli/wham_pp.py
mstk/data/forcefield/SPICA_v1.0.zff
mstk/data/forcefield/gaff.smt
mstk/data/forcefield/gaff.zff
mstk/data/forcefield/primitive.smt
mstk/data/forcefield/primitive.zff
mstk/forcefield/__init__.py
mstk/forcefield/errors.py
mstk/forcefield/ffterm.py
mstk/forcefield/forcefield.py
mstk/forcefield/io/__init__.py
mstk/forcefield/io/padua.py
mstk/forcefield/io/ppf.py
mstk/forcefield/io/zff.py
mstk/forcefield/io/zfp.py
mstk/forcefield/typer/__init__.py
mstk/forcefield/typer/gaff_typer.py
mstk/forcefield/typer/smarts_typer.py
mstk/forcefield/typer/typer.py
mstk/misc/__init__.py
mstk/misc/docmeta.py
mstk/misc/singleton.py
mstk/ommhelper/__init__.py
mstk/ommhelper/force.py
mstk/ommhelper/grofile.py
mstk/ommhelper/unit.py
mstk/ommhelper/utils.py
mstk/ommhelper/reporter/__init__.py
mstk/ommhelper/reporter/checkpointreporter.py
mstk/ommhelper/reporter/drudetemperaturereporter.py
mstk/ommhelper/reporter/groreporter.py
mstk/ommhelper/reporter/maxforcereporter.py
mstk/ommhelper/reporter/statedatareporter.py
mstk/ommhelper/reporter/viscosityreporter.py
mstk/scheduler/__init__.py
mstk/scheduler/pbsjob.py
mstk/scheduler/remote_slurm.py
mstk/scheduler/scheduler.py
mstk/scheduler/slurm.py
mstk/simsys/__init__.py
mstk/simsys/gmxexporter.py
mstk/simsys/lmpexporter.py
mstk/simsys/namdexporter.py
mstk/simsys/ommexporter.py
mstk/simsys/system.py
mstk/topology/__init__.py
mstk/topology/atom.py
mstk/topology/connectivity.py
mstk/topology/geometry.py
mstk/topology/molecule.py
mstk-0.3.29.dist-info/licenses/LICENSE
mstk-0.3.29.dist-info/METADATA
mstk-0.3.29.dist-info/WHEEL
mstk-0.3.29.dist-info/entry_points.txt
mstk-0.3.29.dist-info/top_level.txt
mstk-0.3.29.dist-info/RECORD
