Metadata-Version: 2.4
Name: mstk
Version: 0.3.29
Summary: Molecular simulation toolkit
Author-email: Zheng Gong <z.gong@outlook.com>
Project-URL: Homepage, https://github.com/z-gong/mstk
Classifier: Operating System :: OS Independent
License-File: LICENSE
Dynamic: license-file
